hypod/__init__.py
hypod/_version.py
hypod/decor.py
hypod/main.py
hypod/parser.py
hypod-0.1.2.dist-info/LICENSE
hypod-0.1.2.dist-info/METADATA
hypod-0.1.2.dist-info/WHEEL
hypod-0.1.2.dist-info/top_level.txt
hypod-0.1.2.dist-info/RECORD
