Metadata-Version: 2.1
Name: hypod
Version: 0.1.2
Summary: Hypod: A dataclass-based hyperparameter managing system
Author-email: Jiseob Kim <justjest@gmail.com>
License: MIT License
Project-URL: repository, https://github.com/delta-func/hypod
Keywords: hyperparameter,dataclass,command-line
Classifier: Programming Language :: Python :: 3
Classifier: License :: OSI Approved :: MIT License
Classifier: Operating System :: OS Independent
Requires-Python: >=3.8
License-File: LICENSE
Requires-Dist: typeguard ==3.*
Requires-Dist: pyyaml
